tfs_seon_client/__init__.py
tfs_seon_client/factory/__init__.py
tfs_seon_client/factory/factory.py
tfs_seon_client/factory/service_enum.py
tfs_seon_client/service/__init__.py
tfs_seon_client/service/tfs_service.py
devops_seon_sspo_client-1.0.0.dist-info/METADATA
devops_seon_sspo_client-1.0.0.dist-info/WHEEL
devops_seon_sspo_client-1.0.0.dist-info/top_level.txt
devops_seon_sspo_client-1.0.0.dist-info/RECORD
